{"cameraMode":{"drawMode":2,"name":"Shaded Wireframe","section":"Shading Mode"},"sceneLighting":true,"audioPlay":false,"sceneViewState":{"m_AlwaysRefresh":true,"showFog":true,"showSkybox":true,"showFlares":true,"showImageEffects":true,"showParticleSystems":true,"showVisualEffectGraphs":true,"m_FxEnabled":true},"in2DMode":false,"pivot":{"x":600.0,"y":1419.99658203125,"z":0.0},"rotation":{"x":0.16860303282737733,"y":0.44689419865608218,"z":-0.08618537336587906,"w":0.8743466138839722},"size":1619.318359375,"orthographic":false}